[
    {
        "data": {
            "Pipelines": "`ERPCov+MDM`_",
            ":class:`BNCI2014_008`": "74.30\u00b19.77",
            ":class:`BNCI2014_009`": "81.16\u00b110.13",
            ":class:`BNCI2015_003`": "76.79\u00b110.95",
            ":class:`BI2012`": "78.77\u00b110.32",
            ":class:`BI2013a`": "80.59\u00b19.36",
            ":class:`BI2014a`": "71.62\u00b111.17",
            ":class:`BI2014b`": "78.57\u00b112.36",
            ":class:`BI2015a`": "80.02\u00b110.07",
            ":class:`BI2015b`": "75.04\u00b115.85",
            ":class:`Cattan2019_VR`": "80.76\u00b110.07",
            ":class:`EPFLP300`": "71.97\u00b110.88",
            ":class:`Huebner2017`": "94.47\u00b18.26",
            ":class:`Huebner2018`": "95.15\u00b13.72",
            ":class:`Lee2019_ERP`": "74.43\u00b113.26",
            ":class:`Sosulski2019`": "68.17\u00b113.59"
        }
    },
    {
        "data": {
            "Pipelines": "`ERPCov(svd_n=4)+MDM`_",
            ":class:`BNCI2014_008`": "75.42\u00b19.91",
            ":class:`BNCI2014_009`": "84.52\u00b18.83",
            ":class:`BNCI2015_003`": "76.93\u00b111.26",
            ":class:`BI2012`": "79.02\u00b110.53",
            ":class:`BI2013a`": "82.07\u00b18.46",
            ":class:`BI2014a`": "72.11\u00b111.64",
            ":class:`BI2014b`": "76.48\u00b112.83",
            ":class:`BI2015a`": "77.92\u00b110.33",
            ":class:`BI2015b`": "77.09\u00b115.81",
            ":class:`Cattan2019_VR`": "80.67\u00b19.47",
            ":class:`EPFLP300`": "71.44\u00b110.20",
            ":class:`Huebner2017`": "96.21\u00b16.50",
            ":class:`Huebner2018`": "96.61\u00b11.89",
            ":class:`Lee2019_ERP`": "82.47\u00b112.56",
            ":class:`Sosulski2019`": "70.63\u00b113.79"
        }
    },
    {
        "data": {
            "Pipelines": "`XDAWN+LDA`_",
            ":class:`BNCI2014_008`": "82.24\u00b15.26",
            ":class:`BNCI2014_009`": "64.03\u00b13.91",
            ":class:`BNCI2015_003`": "78.62\u00b17.19",
            ":class:`BI2012`": "64.41\u00b14.14",
            ":class:`BI2013a`": "76.74\u00b17.16",
            ":class:`BI2014a`": "66.60\u00b17.54",
            ":class:`BI2014b`": "83.73\u00b110.62",
            ":class:`BI2015a`": "76.02\u00b110.46",
            ":class:`BI2015b`": "77.22\u00b113.73",
            ":class:`Cattan2019_VR`": "67.16\u00b16.11",
            ":class:`EPFLP300`": "62.98\u00b15.38",
            ":class:`Huebner2017`": "97.74\u00b12.84",
            ":class:`Huebner2018`": "97.54\u00b11.58",
            ":class:`Lee2019_ERP`": "96.45\u00b13.93",
            ":class:`Sosulski2019`": "67.49\u00b17.44"
        }
    },
    {
        "data": {
            "Pipelines": "`XDAWNCov+MDM`_",
            ":class:`BNCI2014_008`": "77.62\u00b19.81",
            ":class:`BNCI2014_009`": "92.04\u00b15.97",
            ":class:`BNCI2015_003`": "83.08\u00b17.55",
            ":class:`BI2012`": "88.22\u00b15.90",
            ":class:`BI2013a`": "90.97\u00b15.52",
            ":class:`BI2014a`": "80.88\u00b111.01",
            ":class:`BI2014b`": "91.58\u00b110.02",
            ":class:`BI2015a`": "92.57\u00b15.03",
            ":class:`BI2015b`": "83.48\u00b112.05",
            ":class:`Cattan2019_VR`": "88.53\u00b17.34",
            ":class:`EPFLP300`": "83.20\u00b19.05",
            ":class:`Huebner2017`": "98.07\u00b12.09",
            ":class:`Huebner2018`": "97.78\u00b11.04",
            ":class:`Lee2019_ERP`": "97.70\u00b12.68",
            ":class:`Sosulski2019`": "86.07\u00b17.15"
        }
    },
    {
        "data": {
            "Pipelines": "`XDAWNCov+TS+SVM`_",
            ":class:`BNCI2014_008`": "85.61\u00b14.43",
            ":class:`BNCI2014_009`": "93.43\u00b15.11",
            ":class:`BNCI2015_003`": "82.95\u00b18.57",
            ":class:`BI2012`": "90.99\u00b14.79",
            ":class:`BI2013a`": "92.71\u00b14.92",
            ":class:`BI2014a`": "85.77\u00b19.75",
            ":class:`BI2014b`": "91.88\u00b19.94",
            ":class:`BI2015a`": "93.05\u00b14.98",
            ":class:`BI2015b`": "84.56\u00b112.09",
            ":class:`Cattan2019_VR`": "90.68\u00b16.29",
            ":class:`EPFLP300`": "84.29\u00b18.53",
            ":class:`Huebner2017`": "98.69\u00b11.78",
            ":class:`Huebner2018`": "98.47\u00b10.97",
            ":class:`Lee2019_ERP`": "98.41\u00b12.03",
            ":class:`Sosulski2019`": "87.28\u00b16.92"
        }
    }
]
